{"Lorient": [{"value": 116345.64945, "product": "Chemical products", "partner": "France", "group": "import"}, {"value": 9470.0, "product": "Chemical products", "partner": "Monde", "group": "import"}, {"value": 30861.0, "product": "Chemical products", "partner": "Monde", "group": "import"}, {"value": 1177.5, "product": "Chemical products", "partner": "France", "group": "import"}, {"value": 67324.5, "product": "Chemical products", "partner": "France", "group": "export"}, {"value": 114605.7989, "product": "Chemical products", "partner": "Fraude ?", "group": "export"}, {"value": 23047.900076100002, "product": "Crude materials, inedible, except combustibles", "partner": "France", "group": "import"}, {"value": 411793.0, "product": "Crude materials, inedible, except combustibles", "partner": "Monde", "group": "import"}, {"value": 180017.035, "product": "Crude materials, inedible, except combustibles", "partner": "Monde", "group": "import"}, {"value": 119.999998, "product": "Crude materials, inedible, except combustibles", "partner": "France", "group": "import"}, {"value": 303793.30011473, "product": "Crude materials, inedible, except combustibles", "partner": "France", "group": "export"}, {"value": 256043.26507810003, "product": "Crude materials, inedible, except combustibles", "partner": "Fraude ?", "group": "export"}, {"value": 35233.0, "product": "Wool threads and fabrics", "partner": "Monde", "group": "import"}, {"value": 3120.0, "product": "Wool threads and fabrics", "partner": "France", "group": "import"}, {"value": 0, "product": "Wool threads and fabrics", "partner": "France", "group": "export"}, {"value": 38353.0, "product": "Wool threads and fabrics", "partner": "Fraude ?", "group": "export"}, {"value": 36271.560097776, "product": "Leather, wood and paper products", "partner": "France", "group": "import"}, {"value": 73715.0, "product": "Leather, wood and paper products", "partner": "Monde", "group": "import"}, {"value": 54012.5, "product": "Leather, wood and paper products", "partner": "Monde", "group": "import"}, {"value": 12016.0, "product": "Leather, wood and paper products", "partner": "France", "group": "import"}, {"value": 21378.50014, "product": "Leather, wood and paper products", "partner": "France", "group": "export"}, {"value": 43958.060097776004, "product": "Leather, wood and paper products", "partner": "Fraude ?", "group": "export"}, {"value": 7649.3, "product": "Plantation foodstuffs", "partner": "France", "group": "import"}, {"value": 16000.0, "product": "Plantation foodstuffs", "partner": "Monde", "group": "import"}, {"value": 8450.0, "product": "Plantation foodstuffs", "partner": "Monde", "group": "import"}, {"value": 23341.1, "product": "Plantation foodstuffs", "partner": "France", "group": "export"}, {"value": 15319.3, "product": "Plantation foodstuffs", "partner": "Fraude ?", "group": "export"}, {"value": 18784.0, "product": "Other", "partner": "France", "group": "import"}, {"value": 83491.0, "product": "Other", "partner": "Monde", "group": "import"}, {"value": 514040.0, "product": "Other", "partner": "Monde", "group": "import"}, {"value": 216.0, "product": "Other", "partner": "France", "group": "import"}, {"value": 1067534.0, "product": "Other", "partner": "colonies", "group": "import"}, {"value": 5549.6875, "product": "Other", "partner": "France", "group": "export"}, {"value": -1476269.0, "product": "Other", "partner": "Fraude ?", "group": "export"}, {"value": 29407.0, "product": "Silk threads and fabrics", "partner": "France", "group": "import"}, {"value": 47451.0, "product": "Silk threads and fabrics", "partner": "Monde", "group": "import"}, {"value": 28975.0, "product": "Silk threads and fabrics", "partner": "France", "group": "import"}, {"value": 0, "product": "Silk threads and fabrics", "partner": "France", "group": "export"}, {"value": -47019.0, "product": "Silk threads and fabrics", "partner": "Fraude ?", "group": "export"}, {"value": 97818.19009295, "product": "Other industrial products", "partner": "France", "group": "import"}, {"value": 1122852.0, "product": "Other industrial products", "partner": "Monde", "group": "import"}, {"value": 35168.0, "product": "Other industrial products", "partner": "Monde", "group": "import"}, {"value": 1422.0, "product": "Other industrial products", "partner": "France", "group": "import"}, {"value": 146722.43052661, "product": "Other industrial products", "partner": "France", "group": "export"}, {"value": 1212486.49008856, "product": "Other industrial products", "partner": "Fraude ?", "group": "export"}, {"value": 16608.35, "product": "Oils", "partner": "France", "group": "import"}, {"value": 185741.7988, "product": "Oils", "partner": "Monde", "group": "import"}, {"value": 868.40002171, "product": "Oils", "partner": "Monde", "group": "import"}, {"value": 104671.9, "product": "Oils", "partner": "France", "group": "export"}, {"value": 202705.74877829, "product": "Oils", "partner": "Fraude ?", "group": "export"}, {"value": 155835.82080133999, "product": "Drinks and tobacco", "partner": "France", "group": "import"}, {"value": 513694.0, "product": "Drinks and tobacco", "partner": "Monde", "group": "import"}, {"value": 497943.25, "product": "Drinks and tobacco", "partner": "Monde", "group": "import"}, {"value": 349.5, "product": "Drinks and tobacco", "partner": "France", "group": "import"}, {"value": 240610.1040027, "product": "Drinks and tobacco", "partner": "France", "group": "export"}, {"value": 226029.57080134004, "product": "Drinks and tobacco", "partner": "Fraude ?", "group": "export"}, {"value": 0, "product": "Precious metals", "partner": "France", "group": "export"}, {"value": 0, "product": "Precious metals", "partner": "Fraude ?", "group": "export"}, {"value": 28690.5, "product": "Other threads and fabrics", "partner": "France", "group": "import"}, {"value": 35220.0, "product": "Other threads and fabrics", "partner": "Monde", "group": "import"}, {"value": 114902.5, "product": "Other threads and fabrics", "partner": "Monde", "group": "import"}, {"value": 26650.0, "product": "Other threads and fabrics", "partner": "France", "group": "import"}, {"value": 23706.0, "product": "Other threads and fabrics", "partner": "France", "group": "export"}, {"value": -77642.0, "product": "Other threads and fabrics", "partner": "Fraude ?", "group": "export"}, {"value": 67784.70121104, "product": "Other foodstuffs and live animals", "partner": "France", "group": "import"}, {"value": 297974.2, "product": "Other foodstuffs and live animals", "partner": "Monde", "group": "import"}, {"value": 82017.0, "product": "Other foodstuffs and live animals", "partner": "Monde", "group": "import"}, {"value": 3800.000095, "product": "Other foodstuffs and live animals", "partner": "France", "group": "import"}, {"value": 85808.41975542999, "product": "Other foodstuffs and live animals", "partner": "France", "group": "export"}, {"value": 282662.60118420003, "product": "Other foodstuffs and live animals", "partner": "Fraude ?", "group": "export"}, {"value": 9900.0, "product": "Coton threads and fabrics", "partner": "France", "group": "import"}, {"value": 49688.0, "product": "Coton threads and fabrics", "partner": "Monde", "group": "import"}, {"value": 5730.5, "product": "Coton threads and fabrics", "partner": "France", "group": "import"}, {"value": 67055.0, "product": "Coton threads and fabrics", "partner": "France", "group": "export"}, {"value": 54829.5, "product": "Coton threads and fabrics", "partner": "Fraude ?", "group": "export"}], "Bayonne": [{"value": 184943.54957104998, "product": "Chemical products", "partner": "France", "group": "import"}, {"value": 5548.0, "product": "Chemical products", "partner": "colonies", "group": "import"}, {"value": 8341.0, "product": "Chemical products", "partner": "colonies", "group": "import"}, {"value": 97102.750006, "product": "Chemical products", "partner": "France", "group": "export"}, {"value": 182150.54957104998, "product": "Chemical products", "partner": "Fraude ?", "group": "export"}, {"value": 279819.4556017225, "product": "Crude materials, inedible, except combustibles", "partner": "France", "group": "import"}, {"value": 9513.0, "product": "Crude materials, inedible, except combustibles", "partner": "colonies", "group": "import"}, {"value": 10473.0, "product": "Crude materials, inedible, except combustibles", "partner": "colonies", "group": "import"}, {"value": 2423786.98905262, "product": "Crude materials, inedible, except combustibles", "partner": "France", "group": "export"}, {"value": 278859.4556017225, "product": "Crude materials, inedible, except combustibles", "partner": "Fraude ?", "group": "export"}, {"value": 50212.0, "product": "Wool threads and fabrics", "partner": "France", "group": "import"}, {"value": 5550.0, "product": "Wool threads and fabrics", "partner": "France", "group": "export"}, {"value": 50212.0, "product": "Wool threads and fabrics", "partner": "Fraude ?", "group": "export"}, {"value": 78956.59880792, "product": "Leather, wood and paper products", "partner": "France", "group": "import"}, {"value": 34875.0, "product": "Leather, wood and paper products", "partner": "colonies", "group": "import"}, {"value": 1626.0, "product": "Leather, wood and paper products", "partner": "colonies", "group": "import"}, {"value": 183089.0, "product": "Leather, wood and paper products", "partner": "France", "group": "export"}, {"value": 112205.59880792, "product": "Leather, wood and paper products", "partner": "Fraude ?", "group": "export"}, {"value": 4491.8, "product": "Plantation foodstuffs", "partner": "France", "group": "import"}, {"value": 830921.0, "product": "Plantation foodstuffs", "partner": "colonies", "group": "import"}, {"value": 265170.3, "product": "Plantation foodstuffs", "partner": "France", "group": "export"}, {"value": 835412.8, "product": "Plantation foodstuffs", "partner": "Fraude ?", "group": "export"}, {"value": 27674.0, "product": "Other", "partner": "France", "group": "import"}, {"value": 300.0, "product": "Other", "partner": "colonies", "group": "import"}, {"value": 2681.0, "product": "Other", "partner": "colonies", "group": "import"}, {"value": 11355.60005, "product": "Other", "partner": "France", "group": "export"}, {"value": 25293.0, "product": "Other", "partner": "Fraude ?", "group": "export"}, {"value": 19938.0, "product": "Silk threads and fabrics", "partner": "France", "group": "import"}, {"value": 2725.0, "product": "Silk threads and fabrics", "partner": "France", "group": "export"}, {"value": 19938.0, "product": "Silk threads and fabrics", "partner": "Fraude ?", "group": "export"}, {"value": 121375.16002042001, "product": "Other industrial products", "partner": "France", "group": "import"}, {"value": 77318.0, "product": "Other industrial products", "partner": "colonies", "group": "import"}, {"value": 383083.0205796601, "product": "Other industrial products", "partner": "France", "group": "export"}, {"value": 44057.16002042001, "product": "Other industrial products", "partner": "Fraude ?", "group": "export"}, {"value": 146947.0365, "product": "Oils", "partner": "France", "group": "import"}, {"value": 4616.0, "product": "Oils", "partner": "colonies", "group": "import"}, {"value": 91361.2003012, "product": "Oils", "partner": "France", "group": "export"}, {"value": 142331.0365, "product": "Oils", "partner": "Fraude ?", "group": "export"}, {"value": 701461.47997965, "product": "Drinks and tobacco", "partner": "France", "group": "import"}, {"value": 4566.0, "product": "Drinks and tobacco", "partner": "colonies", "group": "import"}, {"value": 162777.0, "product": "Drinks and tobacco", "partner": "colonies", "group": "import"}, {"value": 159128.61599999998, "product": "Drinks and tobacco", "partner": "France", "group": "export"}, {"value": 543250.47997965, "product": "Drinks and tobacco", "partner": "Fraude ?", "group": "export"}, {"value": 1170.0, "product": "Precious metals", "partner": "France", "group": "export"}, {"value": 0, "product": "Precious metals", "partner": "Fraude ?", "group": "export"}, {"value": 241124.60021559, "product": "Other threads and fabrics", "partner": "France", "group": "import"}, {"value": 58800.0, "product": "Other threads and fabrics", "partner": "colonies", "group": "import"}, {"value": 13021.0, "product": "Other threads and fabrics", "partner": "France", "group": "export"}, {"value": 182324.60021559, "product": "Other threads and fabrics", "partner": "Fraude ?", "group": "export"}, {"value": 1538176.2249276056, "product": "Other foodstuffs and live animals", "partner": "France", "group": "import"}, {"value": 4885.0, "product": "Other foodstuffs and live animals", "partner": "colonies", "group": "import"}, {"value": 173532.0, "product": "Other foodstuffs and live animals", "partner": "colonies", "group": "import"}, {"value": 1373671.42923328, "product": "Other foodstuffs and live animals", "partner": "France", "group": "export"}, {"value": 1369529.2249276056, "product": "Other foodstuffs and live animals", "partner": "Fraude ?", "group": "export"}, {"value": 12451.5, "product": "Coton threads and fabrics", "partner": "France", "group": "import"}, {"value": 166344.0, "product": "Coton threads and fabrics", "partner": "France", "group": "export"}, {"value": 12451.5, "product": "Coton threads and fabrics", "partner": "Fraude ?", "group": "export"}], "Marseille": [{"value": 775525.70312688, "product": "Chemical products", "partner": "France", "group": "import"}, {"value": 812862.0, "product": "Chemical products", "partner": "colonies", "group": "import"}, {"value": 7492131.653461499, "product": "Chemical products", "partner": "Monde", "group": "import"}, {"value": 6301990.0234013, "product": "Chemical products", "partner": "Monde", "group": "import"}, {"value": 374389.96968, "product": "Chemical products", "partner": "France", "group": "import"}, {"value": 1697334.0, "product": "Chemical products", "partner": "colonies", "group": "import"}, {"value": 22582858.94093853, "product": "Chemical products", "partner": "France", "group": "export"}, {"value": 707368.613507078, "product": "Chemical products", "partner": "Fraude ?", "group": "export"}, {"value": 1109980.995850666, "product": "Crude materials, inedible, except combustibles", "partner": "France", "group": "import"}, {"value": 22946971.777691305, "product": "Crude materials, inedible, except combustibles", "partner": "Monde", "group": "import"}, {"value": 1187898.0, "product": "Crude materials, inedible, except combustibles", "partner": "colonies", "group": "import"}, {"value": 2951822.4185500015, "product": "Crude materials, inedible, except combustibles", "partner": "Monde", "group": "import"}, {"value": 181257.27047775002, "product": "Crude materials, inedible, except combustibles", "partner": "France", "group": "import"}, {"value": 184365.0, "product": "Crude materials, inedible, except combustibles", "partner": "colonies", "group": "import"}, {"value": 10214373.761076488, "product": "Crude materials, inedible, except combustibles", "partner": "France", "group": "export"}, {"value": 22285665.584514223, "product": "Crude materials, inedible, except combustibles", "partner": "Fraude ?", "group": "export"}, {"value": 13455862.5, "product": "Wool threads and fabrics", "partner": "France", "group": "import"}, {"value": 6242776.5901420005, "product": "Wool threads and fabrics", "partner": "Monde", "group": "import"}, {"value": 13184925.5, "product": "Wool threads and fabrics", "partner": "France", "group": "import"}, {"value": 11583111.699996203, "product": "Wool threads and fabrics", "partner": "Monde", "group": "import"}, {"value": 197015.0, "product": "Wool threads and fabrics", "partner": "colonies", "group": "import"}, {"value": 4549371.855, "product": "Wool threads and fabrics", "partner": "France", "group": "export"}, {"value": -5266413.109854203, "product": "Wool threads and fabrics", "partner": "Fraude ?", "group": "export"}, {"value": 1516085.3104912823, "product": "Leather, wood and paper products", "partner": "France", "group": "import"}, {"value": 3286488.0620812, "product": "Leather, wood and paper products", "partner": "Monde", "group": "import"}, {"value": 317375.0, "product": "Leather, wood and paper products", "partner": "colonies", "group": "import"}, {"value": 61921.050339999994, "product": "Leather, wood and paper products", "partner": "France", "group": "import"}, {"value": 1209533.2867897, "product": "Leather, wood and paper products", "partner": "Monde", "group": "import"}, {"value": 460315.0, "product": "Leather, wood and paper products", "partner": "colonies", "group": "import"}, {"value": 3361353.548533322, "product": "Leather, wood and paper products", "partner": "France", "group": "export"}, {"value": 3510515.5557187824, "product": "Leather, wood and paper products", "partner": "Fraude ?", "group": "export"}, {"value": 29202350.0, "product": "Plantation foodstuffs", "partner": "colonies", "group": "import"}, {"value": 2351110.62477975, "product": "Plantation foodstuffs", "partner": "Monde", "group": "import"}, {"value": 16869.6, "product": "Plantation foodstuffs", "partner": "France", "group": "import"}, {"value": 23252475.2031105, "product": "Plantation foodstuffs", "partner": "Monde", "group": "import"}, {"value": 41364.0, "product": "Plantation foodstuffs", "partner": "France", "group": "import"}, {"value": 67219.0, "product": "Plantation foodstuffs", "partner": "colonies", "group": "import"}, {"value": 3762351.4551561, "product": "Plantation foodstuffs", "partner": "France", "group": "export"}, {"value": 8216602.6216692515, "product": "Plantation foodstuffs", "partner": "Fraude ?", "group": "export"}, {"value": 3157255.64217973, "product": "Other", "partner": "France", "group": "import"}, {"value": 351292.23803380004, "product": "Other", "partner": "Monde", "group": "import"}, {"value": 17782.0, "product": "Other", "partner": "colonies", "group": "import"}, {"value": 1293795.90053, "product": "Other", "partner": "France", "group": "import"}, {"value": 873680.1504149999, "product": "Other", "partner": "Monde", "group": "import"}, {"value": 1934464.0, "product": "Other", "partner": "colonies", "group": "import"}, {"value": 1188083.62485026, "product": "Other", "partner": "France", "group": "export"}, {"value": -427739.47065146966, "product": "Other", "partner": "Fraude ?", "group": "export"}, {"value": 4812631.71005, "product": "Silk threads and fabrics", "partner": "France", "group": "import"}, {"value": 5348675.0, "product": "Silk threads and fabrics", "partner": "Monde", "group": "import"}, {"value": 4673978.0, "product": "Silk threads and fabrics", "partner": "France", "group": "import"}, {"value": 3861234.0, "product": "Silk threads and fabrics", "partner": "Monde", "group": "import"}, {"value": 625748.0, "product": "Silk threads and fabrics", "partner": "colonies", "group": "import"}, {"value": 5319.0, "product": "Silk threads and fabrics", "partner": "France", "group": "export"}, {"value": 1000346.7100499999, "product": "Silk threads and fabrics", "partner": "Fraude ?", "group": "export"}, {"value": 4017321.76462729, "product": "Other industrial products", "partner": "France", "group": "import"}, {"value": 5202858.56769418, "product": "Other industrial products", "partner": "Monde", "group": "import"}, {"value": 2822071.7303139996, "product": "Other industrial products", "partner": "France", "group": "import"}, {"value": 3591089.492147399, "product": "Other industrial products", "partner": "Monde", "group": "import"}, {"value": 4944139.0, "product": "Other industrial products", "partner": "colonies", "group": "import"}, {"value": 3765029.5837848596, "product": "Other industrial products", "partner": "France", "group": "export"}, {"value": -2046799.6387399286, "product": "Other industrial products", "partner": "Fraude ?", "group": "export"}, {"value": 2051079.4332270217, "product": "Oils", "partner": "France", "group": "import"}, {"value": 20286512.494104, "product": "Oils", "partner": "Monde", "group": "import"}, {"value": 1946411.9312804, "product": "Oils", "partner": "Monde", "group": "import"}, {"value": 157687.06999625, "product": "Oils", "partner": "France", "group": "import"}, {"value": 956397.0, "product": "Oils", "partner": "colonies", "group": "import"}, {"value": 2393525.02190862, "product": "Oils", "partner": "France", "group": "export"}, {"value": 19298851.816054374, "product": "Oils", "partner": "Fraude ?", "group": "export"}, {"value": 2184185.82155777, "product": "Drinks and tobacco", "partner": "France", "group": "import"}, {"value": 506589.51558540005, "product": "Drinks and tobacco", "partner": "Monde", "group": "import"}, {"value": 75368.0, "product": "Drinks and tobacco", "partner": "colonies", "group": "import"}, {"value": 1287949.5667778999, "product": "Drinks and tobacco", "partner": "Monde", "group": "import"}, {"value": 150982.81710644, "product": "Drinks and tobacco", "partner": "France", "group": "import"}, {"value": 1465042.0, "product": "Drinks and tobacco", "partner": "colonies", "group": "import"}, {"value": 458360.03106104996, "product": "Drinks and tobacco", "partner": "France", "group": "export"}, {"value": -131322.04673117027, "product": "Drinks and tobacco", "partner": "Fraude ?", "group": "export"}, {"value": 7270.0, "product": "Precious metals", "partner": "France", "group": "import"}, {"value": 31317.0, "product": "Precious metals", "partner": "Monde", "group": "import"}, {"value": 36989.0, "product": "Precious metals", "partner": "colonies", "group": "import"}, {"value": 3094.0, "product": "Precious metals", "partner": "France", "group": "export"}, {"value": 1598.0, "product": "Precious metals", "partner": "Fraude ?", "group": "export"}, {"value": 3041250.548556, "product": "Other threads and fabrics", "partner": "France", "group": "import"}, {"value": 1665776.808974, "product": "Other threads and fabrics", "partner": "Monde", "group": "import"}, {"value": 1494270.7499775, "product": "Other threads and fabrics", "partner": "France", "group": "import"}, {"value": 989791.23367805, "product": "Other threads and fabrics", "partner": "Monde", "group": "import"}, {"value": 532181.0, "product": "Other threads and fabrics", "partner": "colonies", "group": "import"}, {"value": 127990.259828, "product": "Other threads and fabrics", "partner": "France", "group": "export"}, {"value": 1726611.9736544504, "product": "Other threads and fabrics", "partner": "Fraude ?", "group": "export"}, {"value": 4494938.785433328, "product": "Other foodstuffs and live animals", "partner": "France", "group": "import"}, {"value": 17499895.61697713, "product": "Other foodstuffs and live animals", "partner": "Monde", "group": "import"}, {"value": 33390.0, "product": "Other foodstuffs and live animals", "partner": "colonies", "group": "import"}, {"value": 232275.48307003, "product": "Other foodstuffs and live animals", "partner": "France", "group": "import"}, {"value": 4028625.077713261, "product": "Other foodstuffs and live animals", "partner": "Monde", "group": "import"}, {"value": 1299177.0, "product": "Other foodstuffs and live animals", "partner": "colonies", "group": "import"}, {"value": 10747986.261347685, "product": "Other foodstuffs and live animals", "partner": "France", "group": "export"}, {"value": 16612283.881627172, "product": "Other foodstuffs and live animals", "partner": "Fraude ?", "group": "export"}, {"value": 2234656.25, "product": "Coton threads and fabrics", "partner": "France", "group": "import"}, {"value": 5731464.2014916, "product": "Coton threads and fabrics", "partner": "Monde", "group": "import"}, {"value": 1682571.7508, "product": "Coton threads and fabrics", "partner": "France", "group": "import"}, {"value": 3551437.0063199997, "product": "Coton threads and fabrics", "partner": "Monde", "group": "import"}, {"value": 2211244.0, "product": "Coton threads and fabrics", "partner": "colonies", "group": "import"}, {"value": 1545431.54, "product": "Coton threads and fabrics", "partner": "France", "group": "export"}, {"value": 569769.6943715997, "product": "Coton threads and fabrics", "partner": "Fraude ?", "group": "export"}], "Dunkerque": [{"value": 280877.01974728, "product": "Chemical products", "partner": "France", "group": "import"}, {"value": 508907.0, "product": "Chemical products", "partner": "Monde", "group": "import"}, {"value": 89556.0, "product": "Chemical products", "partner": "colonies", "group": "import"}, {"value": 101042.0, "product": "Chemical products", "partner": "Monde", "group": "import"}, {"value": 16237.0, "product": "Chemical products", "partner": "colonies", "group": "import"}, {"value": 110962.29001099999, "product": "Chemical products", "partner": "France", "group": "export"}, {"value": 762061.01974728, "product": "Chemical products", "partner": "Re-exp ou fraude ?", "group": "export"}, {"value": 331649.11263924994, "product": "Crude materials, inedible, except combustibles", "partner": "France", "group": "import"}, {"value": 2490363.0, "product": "Crude materials, inedible, except combustibles", "partner": "Monde", "group": "import"}, {"value": 1101518.0, "product": "Crude materials, inedible, except combustibles", "partner": "colonies", "group": "import"}, {"value": 719051.0, "product": "Crude materials, inedible, except combustibles", "partner": "Monde", "group": "import"}, {"value": 6630.0, "product": "Crude materials, inedible, except combustibles", "partner": "colonies", "group": "import"}, {"value": 1340701.5201395, "product": "Crude materials, inedible, except combustibles", "partner": "France", "group": "export"}, {"value": 3197849.11263925, "product": "Crude materials, inedible, except combustibles", "partner": "Re-exp ou fraude ?", "group": "export"}, {"value": 123728.0, "product": "Wool threads and fabrics", "partner": "France", "group": "import"}, {"value": 1721100.0, "product": "Wool threads and fabrics", "partner": "Monde", "group": "import"}, {"value": 71104.0, "product": "Wool threads and fabrics", "partner": "colonies", "group": "import"}, {"value": 1376.0, "product": "Wool threads and fabrics", "partner": "France", "group": "export"}, {"value": 1773724.0, "product": "Wool threads and fabrics", "partner": "Re-exp ou fraude ?", "group": "export"}, {"value": 103605.74532503, "product": "Leather, wood and paper products", "partner": "France", "group": "import"}, {"value": 664528.0, "product": "Leather, wood and paper products", "partner": "Monde", "group": "import"}, {"value": 61376.0, "product": "Leather, wood and paper products", "partner": "colonies", "group": "import"}, {"value": 32319.0, "product": "Leather, wood and paper products", "partner": "colonies", "group": "import"}, {"value": 155250.65, "product": "Leather, wood and paper products", "partner": "France", "group": "export"}, {"value": 797190.7453250301, "product": "Leather, wood and paper products", "partner": "Re-exp ou fraude ?", "group": "export"}, {"value": 42550.0, "product": "Plantation foodstuffs", "partner": "France", "group": "import"}, {"value": 7345722.0, "product": "Plantation foodstuffs", "partner": "colonies", "group": "import"}, {"value": 1649675.0, "product": "Plantation foodstuffs", "partner": "Monde", "group": "import"}, {"value": 3394711.0, "product": "Plantation foodstuffs", "partner": "Monde", "group": "import"}, {"value": 436.0, "product": "Plantation foodstuffs", "partner": "colonies", "group": "import"}, {"value": 57275.0, "product": "Plantation foodstuffs", "partner": "France", "group": "export"}, {"value": 5642800.0, "product": "Plantation foodstuffs", "partner": "Fraude ?", "group": "export"}, {"value": 212659.0, "product": "Other", "partner": "France", "group": "import"}, {"value": 760882.0, "product": "Other", "partner": "Monde", "group": "import"}, {"value": 1353.0, "product": "Other", "partner": "colonies", "group": "import"}, {"value": 8932.0, "product": "Other", "partner": "colonies", "group": "import"}, {"value": 14282.320080000001, "product": "Other", "partner": "France", "group": "export"}, {"value": 965962.0, "product": "Other", "partner": "Re-exp ou fraude ?", "group": "export"}, {"value": 218180.0, "product": "Silk threads and fabrics", "partner": "France", "group": "import"}, {"value": 960770.0, "product": "Silk threads and fabrics", "partner": "Monde", "group": "import"}, {"value": 2100.0, "product": "Silk threads and fabrics", "partner": "colonies", "group": "import"}, {"value": 0, "product": "Silk threads and fabrics", "partner": "France", "group": "export"}, {"value": 1176850.0, "product": "Silk threads and fabrics", "partner": "Re-exp ou fraude ?", "group": "export"}, {"value": 314846.200145, "product": "Other industrial products", "partner": "France", "group": "import"}, {"value": 2999118.0, "product": "Other industrial products", "partner": "Monde", "group": "import"}, {"value": 313967.0, "product": "Other industrial products", "partner": "colonies", "group": "import"}, {"value": 141543.23926685, "product": "Other industrial products", "partner": "France", "group": "export"}, {"value": 2999997.200145, "product": "Other industrial products", "partner": "Re-exp ou fraude ?", "group": "export"}, {"value": 67874.50041114, "product": "Oils", "partner": "France", "group": "import"}, {"value": 537431.0, "product": "Oils", "partner": "Monde", "group": "import"}, {"value": 14793.0, "product": "Oils", "partner": "colonies", "group": "import"}, {"value": 23526.56986543, "product": "Oils", "partner": "France", "group": "export"}, {"value": 590512.50041114, "product": "Oils", "partner": "Re-exp ou fraude ?", "group": "export"}, {"value": 1386671.6049512897, "product": "Drinks and tobacco", "partner": "France", "group": "import"}, {"value": 4440210.0, "product": "Drinks and tobacco", "partner": "Monde", "group": "import"}, {"value": 68894.0, "product": "Drinks and tobacco", "partner": "colonies", "group": "import"}, {"value": 345721.0, "product": "Drinks and tobacco", "partner": "Monde", "group": "import"}, {"value": 93596.0, "product": "Drinks and tobacco", "partner": "colonies", "group": "import"}, {"value": 130892.10000436002, "product": "Drinks and tobacco", "partner": "France", "group": "export"}, {"value": 5456458.6049512895, "product": "Drinks and tobacco", "partner": "Re-exp ou fraude ?", "group": "export"}, {"value": 0, "product": "Precious metals", "partner": "France", "group": "export"}, {"value": 0, "product": "Precious metals", "partner": "Re-exp ou fraude ?", "group": "export"}, {"value": 543957.0, "product": "Other threads and fabrics", "partner": "France", "group": "import"}, {"value": 5767681.0, "product": "Other threads and fabrics", "partner": "Monde", "group": "import"}, {"value": 411933.0, "product": "Other threads and fabrics", "partner": "colonies", "group": "import"}, {"value": 27063.59978, "product": "Other threads and fabrics", "partner": "France", "group": "export"}, {"value": 5899705.0, "product": "Other threads and fabrics", "partner": "Re-exp ou fraude ?", "group": "export"}, {"value": 369295.38427342597, "product": "Other foodstuffs and live animals", "partner": "France", "group": "import"}, {"value": 6929264.0, "product": "Other foodstuffs and live animals", "partner": "Monde", "group": "import"}, {"value": 1736.0, "product": "Other foodstuffs and live animals", "partner": "colonies", "group": "import"}, {"value": 390372.0, "product": "Other foodstuffs and live animals", "partner": "colonies", "group": "import"}, {"value": 1184400.059786, "product": "Other foodstuffs and live animals", "partner": "France", "group": "export"}, {"value": 6909923.384273426, "product": "Other foodstuffs and live animals", "partner": "Re-exp ou fraude ?", "group": "export"}, {"value": 99571.0, "product": "Coton threads and fabrics", "partner": "France", "group": "import"}, {"value": 4831856.0, "product": "Coton threads and fabrics", "partner": "Monde", "group": "import"}, {"value": 49084.0, "product": "Coton threads and fabrics", "partner": "colonies", "group": "import"}, {"value": 547605.0, "product": "Coton threads and fabrics", "partner": "France", "group": "export"}, {"value": 4882343.0, "product": "Coton threads and fabrics", "partner": "Re-exp ou fraude ?", "group": "export"}]}